blemli/__init__.py
blemli/data.py
blemli/date.py
blemli/in.py
blemli-0.0.10.dist-info/METADATA
blemli-0.0.10.dist-info/WHEEL
blemli-0.0.10.dist-info/licenses/LICENSE
blemli-0.0.10.dist-info/RECORD
